pyw/__init__.py
pyw/cli/__init__.py
pyw_cli-0.0.0.post2.dist-info/METADATA
pyw_cli-0.0.0.post2.dist-info/WHEEL
pyw_cli-0.0.0.post2.dist-info/licenses/LICENSE
pyw_cli-0.0.0.post2.dist-info/RECORD
