Metadata-Version: 2.4
Name: pyw-cli
Version: 0.0.0.post2
Summary: Typer-based CLI scaffolding (placeholder)
Project-URL: Homepage, https://github.com/pythonWoods/pyw-cli
Project-URL: Documentation, https://pythonwoods.dev/docs/pyw-cli/latest/
Project-URL: Issues, https://github.com/pythonWoods/pyw-cli/issues
Project-URL: Changelog, https://github.com/pythonWoods/pyw-cli/releases
Author: pythonWoods
License: MIT
License-File: LICENSE
Classifier: Development Status :: 2 - Pre-Alpha
Classifier: License :: OSI Approved :: MIT License
Classifier: Programming Language :: Python :: 3 :: Only
Classifier: Programming Language :: Python :: 3.11
Classifier: Typing :: Typed
Requires-Python: >=3.9
Requires-Dist: pyw-core>=0.0.0
Requires-Dist: typer[all]>=0.9
